bootstrap/__init__.py
bootstrap/fields.py
bootstrap/widgets.py
bootstrap/static/css/bootstrap-clockpicker.min.css
bootstrap/static/css/bootstrap-datepicker3.min.css
bootstrap/static/css/daterangepicker.min.css
bootstrap/static/js/bootstrap-clockpicker.min.js
bootstrap/static/js/bootstrap-datepicker.min.js
bootstrap/static/js/jquery.daterangepicker.min.js
bootstrap/static/js/moment-with-locales.min.js
bootstrap/static/js/locales/bootstrap-datepicker-en-CA.min.js
bootstrap/static/js/locales/bootstrap-datepicker.ar-tn.min.js
bootstrap/static/js/locales/bootstrap-datepicker.ar.min.js
bootstrap/static/js/locales/bootstrap-datepicker.az.min.js
bootstrap/static/js/locales/bootstrap-datepicker.bg.min.js
bootstrap/static/js/locales/bootstrap-datepicker.br.min.js
bootstrap/static/js/locales/bootstrap-datepicker.bs.min.js
bootstrap/static/js/locales/bootstrap-datepicker.ca.min.js
bootstrap/static/js/locales/bootstrap-datepicker.cs.min.js
bootstrap/static/js/locales/bootstrap-datepicker.cy.min.js
bootstrap/static/js/locales/bootstrap-datepicker.da.min.js
bootstrap/static/js/locales/bootstrap-datepicker.de.min.js
bootstrap/static/js/locales/bootstrap-datepicker.el.min.js
bootstrap/static/js/locales/bootstrap-datepicker.en-AU.min.js
bootstrap/static/js/locales/bootstrap-datepicker.en-GB.min.js
bootstrap/static/js/locales/bootstrap-datepicker.en-IE.min.js
bootstrap/static/js/locales/bootstrap-datepicker.en-NZ.min.js
bootstrap/static/js/locales/bootstrap-datepicker.en-ZA.min.js
bootstrap/static/js/locales/bootstrap-datepicker.eo.min.js
bootstrap/static/js/locales/bootstrap-datepicker.es.min.js
bootstrap/static/js/locales/bootstrap-datepicker.et.min.js
bootstrap/static/js/locales/bootstrap-datepicker.eu.min.js
bootstrap/static/js/locales/bootstrap-datepicker.fa.min.js
bootstrap/static/js/locales/bootstrap-datepicker.fi.min.js
bootstrap/static/js/locales/bootstrap-datepicker.fo.min.js
bootstrap/static/js/locales/bootstrap-datepicker.fr-CH.min.js
django_bootstrap_components-3.0.2.dist-info/DESCRIPTION.rst
django_bootstrap_components-3.0.2.dist-info/METADATA
django_bootstrap_components-3.0.2.dist-info/RECORD
django_bootstrap_components-3.0.2.dist-info/WHEEL
django_bootstrap_components-3.0.2.dist-info/metadata.json
django_bootstrap_components-3.0.2.dist-info/top_level.txt
