Metadata-Version: 1.1
Name: django-bootstrap-components
Version: 3.0.2
Summary: Bootstrap components and add-ons integrated with Django.
Home-page: https://github.com/damoti/django-bootstrap-components
Author: Lex Berezhny
Author-email: lex@damoti.com
License: BSD
Keywords: django,bootstrap,dart,date,time,datetime,field,widget,form
Platform: UNKNOWN
Classifier: Framework :: Django
Classifier: Intended Audience :: Developers
Classifier: License :: OSI Approved :: BSD License
Classifier: Programming Language :: Python :: 3
Classifier: Operating System :: OS Independent
Classifier: Topic :: Software Development :: Libraries :: Python Modules
Classifier: Topic :: Software Development :: Testing
Classifier: Topic :: Software Development :: User Interfaces
